[
  {
    "id": "nba-20260505-01",
    "league": "nba",
    "startAtJstIso": "2026-05-05T09:00:00+09:00",
    "season": "2025-26",
    "venue": "",
    "roundLabel": "PLAY OFF GAME 1",
    "seasonPhase": "playoffs",
    "countsForRanking": true,
    "playoffRound": "r2",
    "home": { "name": "New York Knicks", "teamId": "nba-knicks" },
    "away": { "name": "Philadelphia 76ers", "teamId": "nba-76ers" },
    "status": "scheduled"
  },
  {
    "id": "nba-20260505-02",
    "league": "nba",
    "startAtJstIso": "2026-05-05T10:30:00+09:00",
    "season": "2025-26",
    "venue": "",
    "roundLabel": "PLAY OFF GAME 1",
    "seasonPhase": "playoffs",
    "countsForRanking": true,
    "playoffRound": "r2",
    "home": { "name": "San Antonio Spurs", "teamId": "nba-spurs" },
    "away": { "name": "Minnesota Timberwolves", "teamId": "nba-timberwolves" },
    "status": "scheduled"
  },
  {
    "id": "nba-20260506-02",
    "league": "nba",
    "startAtJstIso": "2026-05-06T09:30:00+09:00",
    "season": "2025-26",
    "venue": "",
    "roundLabel": "PLAY OFF GAME 1",
    "seasonPhase": "playoffs",
    "countsForRanking": true,
    "playoffRound": "r2",
    "home": { "name": "Oklahoma City Thunder", "teamId": "nba-thunder" },
    "away": { "name": "Los Angeles Lakers", "teamId": "nba-lakers" },
    "status": "scheduled"
  },
  {
    "id": "nba-20260507-01",
    "league": "nba",
    "startAtJstIso": "2026-05-07T08:00:00+09:00",
    "season": "2025-26",
    "venue": "",
    "roundLabel": "PLAY OFF GAME 2",
    "seasonPhase": "playoffs",
    "countsForRanking": true,
    "playoffRound": "r2",
    "home": { "name": "New York Knicks", "teamId": "nba-knicks" },
    "away": { "name": "Philadelphia 76ers", "teamId": "nba-76ers" },
    "status": "scheduled"
  },
  {
    "id": "nba-20260507-02",
    "league": "nba",
    "startAtJstIso": "2026-05-07T10:30:00+09:00",
    "season": "2025-26",
    "venue": "",
    "roundLabel": "PLAY OFF GAME 2",
    "seasonPhase": "playoffs",
    "countsForRanking": true,
    "playoffRound": "r2",
    "home": { "name": "San Antonio Spurs", "teamId": "nba-spurs" },
    "away": { "name": "Minnesota Timberwolves", "teamId": "nba-timberwolves" },
    "status": "scheduled"
  },
  {
    "id": "nba-20260508-02",
    "league": "nba",
    "startAtJstIso": "2026-05-08T10:30:00+09:00",
    "season": "2025-26",
    "venue": "",
    "roundLabel": "PLAY OFF GAME 2",
    "seasonPhase": "playoffs",
    "countsForRanking": true,
    "playoffRound": "r2",
    "home": { "name": "Oklahoma City Thunder", "teamId": "nba-thunder" },
    "away": { "name": "Los Angeles Lakers", "teamId": "nba-lakers" },
    "status": "scheduled"
  },
  {
    "id": "nba-20260509-01",
    "league": "nba",
    "startAtJstIso": "2026-05-09T08:00:00+09:00",
    "season": "2025-26",
    "venue": "",
    "roundLabel": "PLAY OFF GAME 3",
    "seasonPhase": "playoffs",
    "countsForRanking": true,
    "playoffRound": "r2",
    "home": { "name": "Philadelphia 76ers", "teamId": "nba-76ers" },
    "away": { "name": "New York Knicks", "teamId": "nba-knicks" },
    "status": "scheduled"
  },
  {
    "id": "nba-20260509-02",
    "league": "nba",
    "startAtJstIso": "2026-05-09T10:30:00+09:00",
    "season": "2025-26",
    "venue": "",
    "roundLabel": "PLAY OFF GAME 3",
    "seasonPhase": "playoffs",
    "countsForRanking": true,
    "playoffRound": "r2",
    "home": { "name": "Minnesota Timberwolves", "teamId": "nba-timberwolves" },
    "away": { "name": "San Antonio Spurs", "teamId": "nba-spurs" },
    "status": "scheduled"
  },
  {
    "id": "nba-20260510-02",
    "league": "nba",
    "startAtJstIso": "2026-05-10T09:30:00+09:00",
    "season": "2025-26",
    "venue": "",
    "roundLabel": "PLAY OFF GAME 3",
    "seasonPhase": "playoffs",
    "countsForRanking": true,
    "playoffRound": "r2",
    "home": { "name": "Los Angeles Lakers", "teamId": "nba-lakers" },
    "away": { "name": "Oklahoma City Thunder", "teamId": "nba-thunder" },
    "status": "scheduled"
  },
  {
    "id": "nba-20260511-01",
    "league": "nba",
    "startAtJstIso": "2026-05-11T04:30:00+09:00",
    "season": "2025-26",
    "venue": "",
    "roundLabel": "PLAY OFF GAME 4",
    "seasonPhase": "playoffs",
    "countsForRanking": true,
    "playoffRound": "r2",
    "home": { "name": "Philadelphia 76ers", "teamId": "nba-76ers" },
    "away": { "name": "New York Knicks", "teamId": "nba-knicks" },
    "status": "scheduled"
  },
  {
    "id": "nba-20260511-02",
    "league": "nba",
    "startAtJstIso": "2026-05-11T08:30:00+09:00",
    "season": "2025-26",
    "venue": "",
    "roundLabel": "PLAY OFF GAME 4",
    "seasonPhase": "playoffs",
    "countsForRanking": true,
    "playoffRound": "r2",
    "home": { "name": "Minnesota Timberwolves", "teamId": "nba-timberwolves" },
    "away": { "name": "San Antonio Spurs", "teamId": "nba-spurs" },
    "status": "scheduled"
  },
  {
    "id": "nba-20260512-02",
    "league": "nba",
    "startAtJstIso": "2026-05-12T11:30:00+09:00",
    "season": "2025-26",
    "venue": "",
    "roundLabel": "PLAY OFF GAME 4",
    "seasonPhase": "playoffs",
    "countsForRanking": true,
    "playoffRound": "r2",
    "home": { "name": "Los Angeles Lakers", "teamId": "nba-lakers" },
    "away": { "name": "Oklahoma City Thunder", "teamId": "nba-thunder" },
    "status": "scheduled"
  }
]
